unifi_protect_backup/__init__.py
unifi_protect_backup/cli.py
unifi_protect_backup/downloader.py
unifi_protect_backup/downloader_experimental.py
unifi_protect_backup/event_listener.py
unifi_protect_backup/missing_event_checker.py
unifi_protect_backup/notifications.py
unifi_protect_backup/purge.py
unifi_protect_backup/uiprotect_patch.py
unifi_protect_backup/unifi_protect_backup_core.py
unifi_protect_backup/uploader.py
unifi_protect_backup/utils.py
unifi_protect_backup-0.14.1.dist-info/METADATA
unifi_protect_backup-0.14.1.dist-info/WHEEL
unifi_protect_backup-0.14.1.dist-info/entry_points.txt
unifi_protect_backup-0.14.1.dist-info/licenses/LICENSE
unifi_protect_backup-0.14.1.dist-info/RECORD
