Metadata-Version: 2.4
Name: unifi_protect_backup
Version: 0.14.1
Summary: Python tool to backup unifi event clips in realtime.
Project-URL: Homepage, https://github.com/ep1cman/unifi-protect-backup
Author-email: "sebastian.goscik" <sebastian@goscik.com>
License: MIT
License-File: LICENSE
Classifier: Development Status :: 5 - Production/Stable
Classifier: Intended Audience :: Information Technology
Classifier: License :: OSI Approved :: MIT License
Classifier: Natural Language :: English
Classifier: Programming Language :: Python :: 3
Classifier: Programming Language :: Python :: 3.10
Requires-Python: <4.0,>=3.10.0
Requires-Dist: aiohttp==3.12.14
Requires-Dist: aiolimiter>=1.1.0
Requires-Dist: aiorun>=2023.7.2
Requires-Dist: aiosqlite>=0.17.0
Requires-Dist: apprise>=1.5.0
Requires-Dist: async-lru>=2.0.4
Requires-Dist: click==8.0.1
Requires-Dist: expiring-dict>=1.1.0
Requires-Dist: python-dateutil>=2.8.2
Requires-Dist: uiprotect==7.26.0
